ftpleasant/__init__.py
ftpleasant/ftpleasant.py
ftpleasant-0.1.1.dist-info/METADATA
ftpleasant-0.1.1.dist-info/WHEEL
ftpleasant-0.1.1.dist-info/licenses/LICENSE
ftpleasant-0.1.1.dist-info/RECORD
