Metadata-Version: 2.4
Name: ftpleasant
Version: 0.1.1
Summary: A wrapper built on top of python's built-in FTPlib to simplify operations such as uploading or download files from a server
Project-URL: Homepage, https://github.com/bahmoudd/ftpleasant
Project-URL: Issues, https://github.com/bahmoudd/ftpleasant/issues
Project-URL: Documentation, https://github.com/bahmoudd/ftpleasant/blob/master/DOCUMENTATION.md
Author-email: Bahman Altamash <bahman.alta@gmail.com>
License-Expression: MIT
License-File: LICENSE
Classifier: Development Status :: 4 - Beta
Classifier: License :: OSI Approved :: MIT License
Classifier: Operating System :: OS Independent
Classifier: Programming Language :: Python :: 3
Requires-Python: >=3.7
Requires-Dist: python-dateutil>=2.9.0.post0
Requires-Dist: twine>=4.0.2
